<?xml version="1.0" encoding="utf-8" ?><dwsync><file name="smvlogo.jpg" server="yogi.smv.org/wellness/" local="3407245303" remote="12056094932" /><file name="header.jpg" server="yogi.smv.org/wellness/" local="3465916703" remote="12056719472" /><file name="header_master.png" server="yogi.smv.org/wellness/" local="3465916706" remote="12056094932" /><file name="depression_ball_and_chain.jpg" server="yogi.smv.org/wellness/" local="3466075327" remote="12056094932" /><file name="acrobat.gif" server="yogi.smv.org/wellness/" local="3391678339" remote="12056719472" /><file name="audio-icon-14x14.jpg" server="yogi.smv.org/wellness/" local="3391678339" remote="12056094932" /><file name="blockquotegray.png" server="yogi.smv.org/wellness/" local="3391678339" remote="12056719472" /><file name="email.gif" server="yogi.smv.org/wellness/" local="3391678340" remote="12056719472" /><file name="external.gif" server="yogi.smv.org/wellness/" local="3391678340" remote="12056719472" /><file name="favicon.ico" server="yogi.smv.org/wellness/" local="3391678340" remote="12056094932" /><file name="feed-icon-14x14.jpg" server="yogi.smv.org/wellness/" local="3391678340" remote="12056094932" /><file name="Microsoft_Excel.png" server="yogi.smv.org/wellness/" local="3406136781" remote="12056094932" /><file name="Microsoft_PowerPoint.png" server="yogi.smv.org/wellness/" local="3406136756" remote="12056094932" /><file name="Microsoft_Word.png" server="yogi.smv.org/wellness/" local="3406136723" remote="12056094932" /><file name="new.gif" server="yogi.smv.org/wellness/" local="3391678340" remote="12056094932" /><file name="quotes1.gif" server="yogi.smv.org/wellness/" local="3441129772" remote="12056094932" /><file name="rss.png" server="yogi.smv.org/wellness/" local="3392910845" remote="12056094932" /><file name="rss_feed.gif" server="yogi.smv.org/wellness/" local="3391678340" remote="12056094932" /><file name="rssmini.gif" server="yogi.smv.org/wellness/" local="3391678340" remote="12056094932" /><file name="xml.gif" server="yogi.smv.org/wellness/" local="3391678341" remote="12056094932" /><file name="teen_drug_abuse.jpg" server="yogi.smv.org/wellness/" local="3466083219" remote="12056094932" /></dwsync>